aws_lp/__init__.py
aws_lp/config.py
aws_lp/exceptions.py
aws_lp/lastpass.py
aws_lp/main.py
aws_lp/shell.py
aws_lp/utils.py
aws_lp-0.1.4.dist-info/DESCRIPTION.rst
aws_lp-0.1.4.dist-info/METADATA
aws_lp-0.1.4.dist-info/RECORD
aws_lp-0.1.4.dist-info/WHEEL
aws_lp-0.1.4.dist-info/entry_points.txt
aws_lp-0.1.4.dist-info/metadata.json
aws_lp-0.1.4.dist-info/top_level.txt
