Metadata-Version: 2.0
Name: aws-lp
Version: 0.1.4
Summary: Tool for using AWS CLI with LastPass SAML
Home-page: https://github.com/omnibrian/aws-lp
Author: Brian LeBlanc
Author-email: bleblan2@unb.ca
License: GPLv3
Keywords: lastpass aws awscli boto3
Platform: UNKNOWN
Classifier: Environment :: Console
Classifier: Intended Audience :: Developers
Classifier: Intended Audience :: System Administrators
Classifier: License :: OSI Approved :: GNU General Public License v3 (GPLv3)
Classifier: Programming Language :: Python
Classifier: Programming Language :: Python :: 2
Classifier: Programming Language :: Python :: 2.7
Classifier: Programming Language :: Python :: 3
Classifier: Programming Language :: Python :: 3.6
Classifier: Programming Language :: Python :: 3.7
Requires-Dist: awscli
Requires-Dist: boto3
Requires-Dist: click
Requires-Dist: future
Requires-Dist: requests
Requires-Dist: six
